[
  {"Id":1, "path": "/dashboard", "icon": "fa-chart-bar", "label": "Dashboard" },
  {"Id":2, "path": "/settings", "icon": "fa-gear", "label": "Settings" },
  {"Id":3, "path": "/profile", "icon": "fa-user", "label": "Profile" },
  {"Id":4, "path": "/projects", "icon": "fa-diagram-project", "label": "Projects" },
  {"Id":5, "path": "/courses", "icon": "fa-graduation-cap", "label": "Courses" },
  {"Id":6, "path": "/friends", "icon": "fa-circle-user", "label": "Friends" },
  {"Id":7, "path": "/files", "icon": "fa-file", "label": "Files" },
  {"Id":8, "path": "/plans", "icon": "fa-credit-card", "label": "Plans" }
]
